{"results":[{"title":"Ability","path":"/bare-pages/Ability.json","link":"/page/ability.html","numberOfMatches":1},{"title":"Affect","path":"/bare-pages/Affect.json","link":"/page/affect.html","numberOfMatches":1},{"title":"Anywhere","path":"/bare-pages/Anywhere.json","link":"/page/anywhere.html","numberOfMatches":1},{"title":"Ask","path":"/bare-pages/Ask.json","link":"/page/ask.html","numberOfMatches":1},{"title":"Bare","path":"/bare-pages/Bare.json","link":"/page/bare.html","numberOfMatches":1},{"title":"Blank","path":"/bare-pages/Blank.json","link":"/page/blank.html","numberOfMatches":1},{"title":"Brick","path":"/bare-pages/Brick.json","link":"/page/brick.html","numberOfMatches":1},{"title":"Carried","path":"/bare-pages/Carried.json","link":"/page/carried.html","numberOfMatches":1},{"title":"Certainly","path":"/bare-pages/Certainly.json","link":"/page/certainly.html","numberOfMatches":1},{"title":"Circle","path":"/bare-pages/Circle.json","link":"/page/circle.html","numberOfMatches":1},{"title":"Classroom","path":"/bare-pages/Classroom.json","link":"/page/classroom.html","numberOfMatches":1},{"title":"Coat","path":"/bare-pages/Coat.json","link":"/page/coat.html","numberOfMatches":1},{"title":"Conversation","path":"/bare-pages/Conversation.json","link":"/page/conversation.html","numberOfMatches":1},{"title":"Cookies","path":"/bare-pages/Cookies.json","link":"/page/cookies.html","numberOfMatches":1},{"title":"Cool","path":"/bare-pages/Cool.json","link":"/page/cool.html","numberOfMatches":1},{"title":"Cost","path":"/bare-pages/Cost.json","link":"/page/cost.html","numberOfMatches":1},{"title":"Crop","path":"/bare-pages/Crop.json","link":"/page/crop.html","numberOfMatches":1},{"title":"Daily","path":"/bare-pages/Daily.json","link":"/page/daily.html","numberOfMatches":1},{"title":"Damage","path":"/bare-pages/Damage.json","link":"/page/damage.html","numberOfMatches":1},{"title":"Danger","path":"/bare-pages/Danger.json","link":"/page/danger.html","numberOfMatches":1},{"title":"Desk","path":"/bare-pages/Desk.json","link":"/page/desk.html","numberOfMatches":1},{"title":"Distance","path":"/bare-pages/Distance.json","link":"/page/distance.html","numberOfMatches":1},{"title":"Drink","path":"/bare-pages/Drink.json","link":"/page/drink.html","numberOfMatches":1},{"title":"Electricity","path":"/bare-pages/Electricity.json","link":"/page/electricity.html","numberOfMatches":1},{"title":"Enemy","path":"/bare-pages/Enemy.json","link":"/page/enemy.html","numberOfMatches":1},{"title":"Environment","path":"/bare-pages/Environment.json","link":"/page/environment.html","numberOfMatches":1},{"title":"Every","path":"/bare-pages/Every.json","link":"/page/every.html","numberOfMatches":1},{"title":"Factor","path":"/bare-pages/Factor.json","link":"/page/factor.html","numberOfMatches":1},{"title":"Five","path":"/bare-pages/Five.json","link":"/page/five.html","numberOfMatches":1},{"title":"Flame","path":"/bare-pages/Flame.json","link":"/page/flame.html","numberOfMatches":1},{"title":"Glad","path":"/bare-pages/Glad.json","link":"/page/glad.html","numberOfMatches":1},{"title":"Hair","path":"/bare-pages/Hair.json","link":"/page/hair.html","numberOfMatches":1},{"title":"Handle","path":"/bare-pages/Handle.json","link":"/page/handle.html","numberOfMatches":1},{"title":"Have","path":"/bare-pages/Have.json","link":"/page/have.html","numberOfMatches":1},{"title":"Hollow","path":"/bare-pages/Hollow.json","link":"/page/hollow.html","numberOfMatches":1},{"title":"Hurried","path":"/bare-pages/Hurried.json","link":"/page/hurried.html","numberOfMatches":1},{"title":"Loss","path":"/bare-pages/Loss.json","link":"/page/loss.html","numberOfMatches":1},{"title":"Mad","path":"/bare-pages/Mad.json","link":"/page/mad.html","numberOfMatches":1},{"title":"Negative","path":"/bare-pages/Negative.json","link":"/page/negative.html","numberOfMatches":1},{"title":"No","path":"/bare-pages/No.json","link":"/page/no.html","numberOfMatches":1},{"title":"Not","path":"/bare-pages/Not.json","link":"/page/not.html","numberOfMatches":1},{"title":"Original","path":"/bare-pages/Original.json","link":"/page/original.html","numberOfMatches":1},{"title":"Population","path":"/bare-pages/Population.json","link":"/page/population.html","numberOfMatches":1},{"title":"Pupil","path":"/bare-pages/Pupil.json","link":"/page/pupil.html","numberOfMatches":1},{"title":"Quite","path":"/bare-pages/Quite.json","link":"/page/quite.html","numberOfMatches":1},{"title":"Religious","path":"/bare-pages/Religious.json","link":"/page/religious.html","numberOfMatches":1},{"title":"Remove","path":"/bare-pages/Remove.json","link":"/page/remove.html","numberOfMatches":1},{"title":"Replace","path":"/bare-pages/Replace.json","link":"/page/replace.html","numberOfMatches":1},{"title":"Scientific","path":"/bare-pages/Scientific.json","link":"/page/scientific.html","numberOfMatches":1},{"title":"Setting","path":"/bare-pages/Setting.json","link":"/page/setting.html","numberOfMatches":1},{"title":"Shoe","path":"/bare-pages/Shoe.json","link":"/page/shoe.html","numberOfMatches":1},{"title":"Shop","path":"/bare-pages/Shop.json","link":"/page/shop.html","numberOfMatches":1},{"title":"Species","path":"/bare-pages/Species.json","link":"/page/species.html","numberOfMatches":1},{"title":"Star","path":"/bare-pages/Star.json","link":"/page/star.html","numberOfMatches":1},{"title":"Store","path":"/bare-pages/Store.json","link":"/page/store.html","numberOfMatches":1},{"title":"Suit","path":"/bare-pages/Suit.json","link":"/page/suit.html","numberOfMatches":1},{"title":"Vegetable","path":"/bare-pages/Vegetable.json","link":"/page/vegetable.html","numberOfMatches":1},{"title":"Weigh","path":"/bare-pages/Weigh.json","link":"/page/weigh.html","numberOfMatches":1}]}