{"results":[{"title":"Active","path":"/bare-pages/Active.json","link":"/page/active.html","numberOfMatches":1},{"title":"Alone","path":"/bare-pages/Alone.json","link":"/page/alone.html","numberOfMatches":1},{"title":"Any","path":"/bare-pages/Any.json","link":"/page/any.html","numberOfMatches":1},{"title":"Asleep","path":"/bare-pages/Asleep.json","link":"/page/asleep.html","numberOfMatches":1},{"title":"Cell","path":"/bare-pages/Cell.json","link":"/page/cell.html","numberOfMatches":1},{"title":"Central","path":"/bare-pages/Central.json","link":"/page/central.html","numberOfMatches":1},{"title":"Clay","path":"/bare-pages/Clay.json","link":"/page/clay.html","numberOfMatches":1},{"title":"Cookies","path":"/bare-pages/Cookies.json","link":"/page/cookies.html","numberOfMatches":1},{"title":"Cowboy","path":"/bare-pages/Cowboy.json","link":"/page/cowboy.html","numberOfMatches":2},{"title":"Degree","path":"/bare-pages/Degree.json","link":"/page/degree.html","numberOfMatches":1},{"title":"Depend","path":"/bare-pages/Depend.json","link":"/page/depend.html","numberOfMatches":1},{"title":"Distant","path":"/bare-pages/Distant.json","link":"/page/distant.html","numberOfMatches":1},{"title":"Divide","path":"/bare-pages/Divide.json","link":"/page/divide.html","numberOfMatches":1},{"title":"Drew","path":"/bare-pages/Drew.json","link":"/page/drew.html","numberOfMatches":1},{"title":"Each","path":"/bare-pages/Each.json","link":"/page/each.html","numberOfMatches":1},{"title":"Event","path":"/bare-pages/Event.json","link":"/page/event.html","numberOfMatches":1},{"title":"Fast","path":"/bare-pages/Fast.json","link":"/page/fast.html","numberOfMatches":1},{"title":"Fifty","path":"/bare-pages/Fifty.json","link":"/page/fifty.html","numberOfMatches":1},{"title":"Fireplace","path":"/bare-pages/Fireplace.json","link":"/page/fireplace.html","numberOfMatches":1},{"title":"Flew","path":"/bare-pages/Flew.json","link":"/page/flew.html","numberOfMatches":2},{"title":"Grow","path":"/bare-pages/Grow.json","link":"/page/grow.html","numberOfMatches":1},{"title":"Have","path":"/bare-pages/Have.json","link":"/page/have.html","numberOfMatches":1},{"title":"Immediately","path":"/bare-pages/Immediately.json","link":"/page/immediately.html","numberOfMatches":2},{"title":"In","path":"/bare-pages/In.json","link":"/page/in.html","numberOfMatches":1},{"title":"Joy","path":"/bare-pages/Joy.json","link":"/page/joy.html","numberOfMatches":1},{"title":"Judge","path":"/bare-pages/Judge.json","link":"/page/judge.html","numberOfMatches":1},{"title":"Kill","path":"/bare-pages/Kill.json","link":"/page/kill.html","numberOfMatches":1},{"title":"Knew","path":"/bare-pages/Knew.json","link":"/page/knew.html","numberOfMatches":1},{"title":"Leaf","path":"/bare-pages/Leaf.json","link":"/page/leaf.html","numberOfMatches":1},{"title":"Limited","path":"/bare-pages/Limited.json","link":"/page/limited.html","numberOfMatches":1},{"title":"Low","path":"/bare-pages/Low.json","link":"/page/low.html","numberOfMatches":1},{"title":"Machine","path":"/bare-pages/Machine.json","link":"/page/machine.html","numberOfMatches":1},{"title":"Magic","path":"/bare-pages/Magic.json","link":"/page/magic.html","numberOfMatches":1},{"title":"Mirror","path":"/bare-pages/Mirror.json","link":"/page/mirror.html","numberOfMatches":1},{"title":"More","path":"/bare-pages/More.json","link":"/page/more.html","numberOfMatches":1},{"title":"Needs","path":"/bare-pages/Needs.json","link":"/page/needs.html","numberOfMatches":1},{"title":"Number","path":"/bare-pages/Number.json","link":"/page/number.html","numberOfMatches":1},{"title":"Orbit","path":"/bare-pages/Orbit.json","link":"/page/orbit.html","numberOfMatches":1},{"title":"Original","path":"/bare-pages/Original.json","link":"/page/original.html","numberOfMatches":1},{"title":"Pig","path":"/bare-pages/Pig.json","link":"/page/pig.html","numberOfMatches":1},{"title":"Play","path":"/bare-pages/Play.json","link":"/page/play.html","numberOfMatches":1},{"title":"Police","path":"/bare-pages/Police.json","link":"/page/police.html","numberOfMatches":1},{"title":"Previous","path":"/bare-pages/Previous.json","link":"/page/previous.html","numberOfMatches":1},{"title":"Probably","path":"/bare-pages/Probably.json","link":"/page/probably.html","numberOfMatches":1},{"title":"Proper","path":"/bare-pages/Proper.json","link":"/page/proper.html","numberOfMatches":1},{"title":"Recognize","path":"/bare-pages/Recognize.json","link":"/page/recognize.html","numberOfMatches":1},{"title":"Refer","path":"/bare-pages/Refer.json","link":"/page/refer.html","numberOfMatches":1},{"title":"Ring","path":"/bare-pages/Ring.json","link":"/page/ring.html","numberOfMatches":1},{"title":"Rush","path":"/bare-pages/Rush.json","link":"/page/rush.html","numberOfMatches":1},{"title":"Save","path":"/bare-pages/Save.json","link":"/page/save.html","numberOfMatches":1},{"title":"Shells","path":"/bare-pages/Shells.json","link":"/page/shells.html","numberOfMatches":1},{"title":"Simplest","path":"/bare-pages/Simplest.json","link":"/page/simplest.html","numberOfMatches":1},{"title":"Smallest","path":"/bare-pages/Smallest.json","link":"/page/smallest.html","numberOfMatches":1},{"title":"Smoke","path":"/bare-pages/Smoke.json","link":"/page/smoke.html","numberOfMatches":1},{"title":"Smooth","path":"/bare-pages/Smooth.json","link":"/page/smooth.html","numberOfMatches":1},{"title":"Spent","path":"/bare-pages/Spent.json","link":"/page/spent.html","numberOfMatches":1},{"title":"Steady","path":"/bare-pages/Steady.json","link":"/page/steady.html","numberOfMatches":1},{"title":"Thousand","path":"/bare-pages/Thousand.json","link":"/page/thousand.html","numberOfMatches":1},{"title":"Warm","path":"/bare-pages/Warm.json","link":"/page/warm.html","numberOfMatches":1},{"title":"Warn","path":"/bare-pages/Warn.json","link":"/page/warn.html","numberOfMatches":1},{"title":"Widely","path":"/bare-pages/Widely.json","link":"/page/widely.html","numberOfMatches":1},{"title":"Writer","path":"/bare-pages/Writer.json","link":"/page/writer.html","numberOfMatches":1}]}