{"results":[{"title":"After","path":"/hulipaa-demo/bare-pages/After.json","link":"/hulipaa-demo/page/after.html","numberOfMatches":1},{"title":"Agree","path":"/hulipaa-demo/bare-pages/Agree.json","link":"/hulipaa-demo/page/agree.html","numberOfMatches":1},{"title":"Among","path":"/hulipaa-demo/bare-pages/Among.json","link":"/hulipaa-demo/page/among.html","numberOfMatches":1},{"title":"Asleep","path":"/hulipaa-demo/bare-pages/Asleep.json","link":"/hulipaa-demo/page/asleep.html","numberOfMatches":1},{"title":"Bicycle","path":"/hulipaa-demo/bare-pages/Bicycle.json","link":"/hulipaa-demo/page/bicycle.html","numberOfMatches":1},{"title":"Border","path":"/hulipaa-demo/bare-pages/Border.json","link":"/hulipaa-demo/page/border.html","numberOfMatches":1},{"title":"Bridge","path":"/hulipaa-demo/bare-pages/Bridge.json","link":"/hulipaa-demo/page/bridge.html","numberOfMatches":1},{"title":"Bring","path":"/hulipaa-demo/bare-pages/Bring.json","link":"/hulipaa-demo/page/bring.html","numberOfMatches":1},{"title":"Brought","path":"/hulipaa-demo/bare-pages/Brought.json","link":"/hulipaa-demo/page/brought.html","numberOfMatches":1},{"title":"Bus","path":"/hulipaa-demo/bare-pages/Bus.json","link":"/hulipaa-demo/page/bus.html","numberOfMatches":1},{"title":"Chose","path":"/hulipaa-demo/bare-pages/Chose.json","link":"/hulipaa-demo/page/chose.html","numberOfMatches":1},{"title":"Climate","path":"/hulipaa-demo/bare-pages/Climate.json","link":"/hulipaa-demo/page/climate.html","numberOfMatches":1},{"title":"Company","path":"/hulipaa-demo/bare-pages/Company.json","link":"/hulipaa-demo/page/company.html","numberOfMatches":1},{"title":"Contrast","path":"/hulipaa-demo/bare-pages/Contrast.json","link":"/hulipaa-demo/page/contrast.html","numberOfMatches":1},{"title":"Drew","path":"/hulipaa-demo/bare-pages/Drew.json","link":"/hulipaa-demo/page/drew.html","numberOfMatches":1},{"title":"During","path":"/hulipaa-demo/bare-pages/During.json","link":"/hulipaa-demo/page/during.html","numberOfMatches":1},{"title":"Escape","path":"/hulipaa-demo/bare-pages/Escape.json","link":"/hulipaa-demo/page/escape.html","numberOfMatches":1},{"title":"Essential","path":"/hulipaa-demo/bare-pages/Essential.json","link":"/hulipaa-demo/page/essential.html","numberOfMatches":1},{"title":"Familiar","path":"/hulipaa-demo/bare-pages/Familiar.json","link":"/hulipaa-demo/page/familiar.html","numberOfMatches":1},{"title":"Family","path":"/hulipaa-demo/bare-pages/Family.json","link":"/hulipaa-demo/page/family.html","numberOfMatches":1},{"title":"Few","path":"/hulipaa-demo/bare-pages/Few.json","link":"/hulipaa-demo/page/few.html","numberOfMatches":1},{"title":"Fewer","path":"/hulipaa-demo/bare-pages/Fewer.json","link":"/hulipaa-demo/page/fewer.html","numberOfMatches":1},{"title":"Finest","path":"/hulipaa-demo/bare-pages/Finest.json","link":"/hulipaa-demo/page/finest.html","numberOfMatches":1},{"title":"Finish","path":"/hulipaa-demo/bare-pages/Finish.json","link":"/hulipaa-demo/page/finish.html","numberOfMatches":1},{"title":"Flew","path":"/hulipaa-demo/bare-pages/Flew.json","link":"/hulipaa-demo/page/flew.html","numberOfMatches":1},{"title":"Flower","path":"/hulipaa-demo/bare-pages/Flower.json","link":"/hulipaa-demo/page/flower.html","numberOfMatches":1},{"title":"Globe","path":"/hulipaa-demo/bare-pages/Globe.json","link":"/hulipaa-demo/page/globe.html","numberOfMatches":1},{"title":"Grabbed","path":"/hulipaa-demo/bare-pages/Grabbed.json","link":"/hulipaa-demo/page/grabbed.html","numberOfMatches":1},{"title":"Graph","path":"/hulipaa-demo/bare-pages/Graph.json","link":"/hulipaa-demo/page/graph.html","numberOfMatches":1},{"title":"Guess","path":"/hulipaa-demo/bare-pages/Guess.json","link":"/hulipaa-demo/page/guess.html","numberOfMatches":1},{"title":"Held","path":"/hulipaa-demo/bare-pages/Held.json","link":"/hulipaa-demo/page/held.html","numberOfMatches":1},{"title":"Higher","path":"/hulipaa-demo/bare-pages/Higher.json","link":"/hulipaa-demo/page/higher.html","numberOfMatches":1},{"title":"Hill","path":"/hulipaa-demo/bare-pages/Hill.json","link":"/hulipaa-demo/page/hill.html","numberOfMatches":1},{"title":"Him","path":"/hulipaa-demo/bare-pages/Him.json","link":"/hulipaa-demo/page/him.html","numberOfMatches":1},{"title":"Indicate","path":"/hulipaa-demo/bare-pages/Indicate.json","link":"/hulipaa-demo/page/indicate.html","numberOfMatches":1},{"title":"Interest","path":"/hulipaa-demo/bare-pages/Interest.json","link":"/hulipaa-demo/page/interest.html","numberOfMatches":1},{"title":"Involved","path":"/hulipaa-demo/bare-pages/Involved.json","link":"/hulipaa-demo/page/involved.html","numberOfMatches":1},{"title":"Joined","path":"/hulipaa-demo/bare-pages/Joined.json","link":"/hulipaa-demo/page/joined.html","numberOfMatches":1},{"title":"Life","path":"/hulipaa-demo/bare-pages/Life.json","link":"/hulipaa-demo/page/life.html","numberOfMatches":1},{"title":"Lungs","path":"/hulipaa-demo/bare-pages/Lungs.json","link":"/hulipaa-demo/page/lungs.html","numberOfMatches":1},{"title":"Man","path":"/hulipaa-demo/bare-pages/Man.json","link":"/hulipaa-demo/page/man.html","numberOfMatches":1},{"title":"Map","path":"/hulipaa-demo/bare-pages/Map.json","link":"/hulipaa-demo/page/map.html","numberOfMatches":1},{"title":"Mass","path":"/hulipaa-demo/bare-pages/Mass.json","link":"/hulipaa-demo/page/mass.html","numberOfMatches":1},{"title":"Memory","path":"/hulipaa-demo/bare-pages/Memory.json","link":"/hulipaa-demo/page/memory.html","numberOfMatches":1},{"title":"Method","path":"/hulipaa-demo/bare-pages/Method.json","link":"/hulipaa-demo/page/method.html","numberOfMatches":1},{"title":"Mill","path":"/hulipaa-demo/bare-pages/Mill.json","link":"/hulipaa-demo/page/mill.html","numberOfMatches":1},{"title":"Mostly","path":"/hulipaa-demo/bare-pages/Mostly.json","link":"/hulipaa-demo/page/mostly.html","numberOfMatches":1},{"title":"Natural","path":"/hulipaa-demo/bare-pages/Natural.json","link":"/hulipaa-demo/page/natural.html","numberOfMatches":1},{"title":"Numeral","path":"/hulipaa-demo/bare-pages/Numeral.json","link":"/hulipaa-demo/page/numeral.html","numberOfMatches":1},{"title":"Onto","path":"/hulipaa-demo/bare-pages/Onto.json","link":"/hulipaa-demo/page/onto.html","numberOfMatches":1},{"title":"Ordinary","path":"/hulipaa-demo/bare-pages/Ordinary.json","link":"/hulipaa-demo/page/ordinary.html","numberOfMatches":1},{"title":"Paint","path":"/hulipaa-demo/bare-pages/Paint.json","link":"/hulipaa-demo/page/paint.html","numberOfMatches":1},{"title":"Period","path":"/hulipaa-demo/bare-pages/Period.json","link":"/hulipaa-demo/page/period.html","numberOfMatches":1},{"title":"Personal","path":"/hulipaa-demo/bare-pages/Personal.json","link":"/hulipaa-demo/page/personal.html","numberOfMatches":1},{"title":"Pie","path":"/hulipaa-demo/bare-pages/Pie.json","link":"/hulipaa-demo/page/pie.html","numberOfMatches":1},{"title":"Pleasant","path":"/hulipaa-demo/bare-pages/Pleasant.json","link":"/hulipaa-demo/page/pleasant.html","numberOfMatches":1},{"title":"Plural","path":"/hulipaa-demo/bare-pages/Plural.json","link":"/hulipaa-demo/page/plural.html","numberOfMatches":1},{"title":"Pole","path":"/hulipaa-demo/bare-pages/Pole.json","link":"/hulipaa-demo/page/pole.html","numberOfMatches":1},{"title":"Policeman","path":"/hulipaa-demo/bare-pages/Policeman.json","link":"/hulipaa-demo/page/policeman.html","numberOfMatches":1},{"title":"Pony","path":"/hulipaa-demo/bare-pages/Pony.json","link":"/hulipaa-demo/page/pony.html","numberOfMatches":1},{"title":"Rapidly","path":"/hulipaa-demo/bare-pages/Rapidly.json","link":"/hulipaa-demo/page/rapidly.html","numberOfMatches":1},{"title":"Recent","path":"/hulipaa-demo/bare-pages/Recent.json","link":"/hulipaa-demo/page/recent.html","numberOfMatches":1},{"title":"Sail","path":"/hulipaa-demo/bare-pages/Sail.json","link":"/hulipaa-demo/page/sail.html","numberOfMatches":1},{"title":"Season","path":"/hulipaa-demo/bare-pages/Season.json","link":"/hulipaa-demo/page/season.html","numberOfMatches":1},{"title":"Seat","path":"/hulipaa-demo/bare-pages/Seat.json","link":"/hulipaa-demo/page/seat.html","numberOfMatches":1},{"title":"Sets","path":"/hulipaa-demo/bare-pages/Sets.json","link":"/hulipaa-demo/page/sets.html","numberOfMatches":1},{"title":"Shop","path":"/hulipaa-demo/bare-pages/Shop.json","link":"/hulipaa-demo/page/shop.html","numberOfMatches":1},{"title":"Single","path":"/hulipaa-demo/bare-pages/Single.json","link":"/hulipaa-demo/page/single.html","numberOfMatches":1},{"title":"Sleep","path":"/hulipaa-demo/bare-pages/Sleep.json","link":"/hulipaa-demo/page/sleep.html","numberOfMatches":1},{"title":"Some","path":"/hulipaa-demo/bare-pages/Some.json","link":"/hulipaa-demo/page/some.html","numberOfMatches":1},{"title":"Son","path":"/hulipaa-demo/bare-pages/Son.json","link":"/hulipaa-demo/page/son.html","numberOfMatches":1},{"title":"Stiff","path":"/hulipaa-demo/bare-pages/Stiff.json","link":"/hulipaa-demo/page/stiff.html","numberOfMatches":1},{"title":"Stood","path":"/hulipaa-demo/bare-pages/Stood.json","link":"/hulipaa-demo/page/stood.html","numberOfMatches":1},{"title":"Store","path":"/hulipaa-demo/bare-pages/Store.json","link":"/hulipaa-demo/page/store.html","numberOfMatches":1},{"title":"Supper","path":"/hulipaa-demo/bare-pages/Supper.json","link":"/hulipaa-demo/page/supper.html","numberOfMatches":1},{"title":"Surrounded","path":"/hulipaa-demo/bare-pages/Surrounded.json","link":"/hulipaa-demo/page/surrounded.html","numberOfMatches":1},{"title":"Take","path":"/hulipaa-demo/bare-pages/Take.json","link":"/hulipaa-demo/page/take.html","numberOfMatches":1},{"title":"Television","path":"/hulipaa-demo/bare-pages/Television.json","link":"/hulipaa-demo/page/television.html","numberOfMatches":1},{"title":"Thumb","path":"/hulipaa-demo/bare-pages/Thumb.json","link":"/hulipaa-demo/page/thumb.html","numberOfMatches":1},{"title":"Typical","path":"/hulipaa-demo/bare-pages/Typical.json","link":"/hulipaa-demo/page/typical.html","numberOfMatches":1},{"title":"Use","path":"/hulipaa-demo/bare-pages/Use.json","link":"/hulipaa-demo/page/use.html","numberOfMatches":1},{"title":"Vast","path":"/hulipaa-demo/bare-pages/Vast.json","link":"/hulipaa-demo/page/vast.html","numberOfMatches":1},{"title":"Waste","path":"/hulipaa-demo/bare-pages/Waste.json","link":"/hulipaa-demo/page/waste.html","numberOfMatches":1},{"title":"Wet","path":"/hulipaa-demo/bare-pages/Wet.json","link":"/hulipaa-demo/page/wet.html","numberOfMatches":1},{"title":"Widely","path":"/hulipaa-demo/bare-pages/Widely.json","link":"/hulipaa-demo/page/widely.html","numberOfMatches":1},{"title":"Wore","path":"/hulipaa-demo/bare-pages/Wore.json","link":"/hulipaa-demo/page/wore.html","numberOfMatches":1},{"title":"Wrong","path":"/hulipaa-demo/bare-pages/Wrong.json","link":"/hulipaa-demo/page/wrong.html","numberOfMatches":1}]}