{"results":[{"title":"Age","path":"/hulipaa-demo/bare-pages/Age.json","link":"/hulipaa-demo/page/age.html","numberOfMatches":1},{"title":"Ahead","path":"/hulipaa-demo/bare-pages/Ahead.json","link":"/hulipaa-demo/page/ahead.html","numberOfMatches":1},{"title":"Although","path":"/hulipaa-demo/bare-pages/Although.json","link":"/hulipaa-demo/page/although.html","numberOfMatches":1},{"title":"Arrow","path":"/hulipaa-demo/bare-pages/Arrow.json","link":"/hulipaa-demo/page/arrow.html","numberOfMatches":1},{"title":"Atom","path":"/hulipaa-demo/bare-pages/Atom.json","link":"/hulipaa-demo/page/atom.html","numberOfMatches":1},{"title":"Audience","path":"/hulipaa-demo/bare-pages/Audience.json","link":"/hulipaa-demo/page/audience.html","numberOfMatches":1},{"title":"Automobile","path":"/hulipaa-demo/bare-pages/Automobile.json","link":"/hulipaa-demo/page/automobile.html","numberOfMatches":1},{"title":"Become","path":"/hulipaa-demo/bare-pages/Become.json","link":"/hulipaa-demo/page/become.html","numberOfMatches":1},{"title":"Blew","path":"/hulipaa-demo/bare-pages/Blew.json","link":"/hulipaa-demo/page/blew.html","numberOfMatches":1},{"title":"Box","path":"/hulipaa-demo/bare-pages/Box.json","link":"/hulipaa-demo/page/box.html","numberOfMatches":1},{"title":"Break","path":"/hulipaa-demo/bare-pages/Break.json","link":"/hulipaa-demo/page/break.html","numberOfMatches":1},{"title":"Bridge","path":"/hulipaa-demo/bare-pages/Bridge.json","link":"/hulipaa-demo/page/bridge.html","numberOfMatches":1},{"title":"Car","path":"/hulipaa-demo/bare-pages/Car.json","link":"/hulipaa-demo/page/car.html","numberOfMatches":1},{"title":"Clearly","path":"/hulipaa-demo/bare-pages/Clearly.json","link":"/hulipaa-demo/page/clearly.html","numberOfMatches":1},{"title":"Common","path":"/hulipaa-demo/bare-pages/Common.json","link":"/hulipaa-demo/page/common.html","numberOfMatches":1},{"title":"Cost","path":"/hulipaa-demo/bare-pages/Cost.json","link":"/hulipaa-demo/page/cost.html","numberOfMatches":2},{"title":"Current","path":"/hulipaa-demo/bare-pages/Current.json","link":"/hulipaa-demo/page/current.html","numberOfMatches":1},{"title":"Direct","path":"/hulipaa-demo/bare-pages/Direct.json","link":"/hulipaa-demo/page/direct.html","numberOfMatches":1},{"title":"Equator","path":"/hulipaa-demo/bare-pages/Equator.json","link":"/hulipaa-demo/page/equator.html","numberOfMatches":1},{"title":"Famous","path":"/hulipaa-demo/bare-pages/Famous.json","link":"/hulipaa-demo/page/famous.html","numberOfMatches":1},{"title":"Feed","path":"/hulipaa-demo/bare-pages/Feed.json","link":"/hulipaa-demo/page/feed.html","numberOfMatches":1},{"title":"Find","path":"/hulipaa-demo/bare-pages/Find.json","link":"/hulipaa-demo/page/find.html","numberOfMatches":1},{"title":"Floor","path":"/hulipaa-demo/bare-pages/Floor.json","link":"/hulipaa-demo/page/floor.html","numberOfMatches":1},{"title":"Give","path":"/hulipaa-demo/bare-pages/Give.json","link":"/hulipaa-demo/page/give.html","numberOfMatches":1},{"title":"Grandfather","path":"/hulipaa-demo/bare-pages/Grandfather.json","link":"/hulipaa-demo/page/grandfather.html","numberOfMatches":1},{"title":"Grass","path":"/hulipaa-demo/bare-pages/Grass.json","link":"/hulipaa-demo/page/grass.html","numberOfMatches":1},{"title":"Habit","path":"/hulipaa-demo/bare-pages/Habit.json","link":"/hulipaa-demo/page/habit.html","numberOfMatches":1},{"title":"Has","path":"/hulipaa-demo/bare-pages/Has.json","link":"/hulipaa-demo/page/has.html","numberOfMatches":1},{"title":"Hat","path":"/hulipaa-demo/bare-pages/Hat.json","link":"/hulipaa-demo/page/hat.html","numberOfMatches":1},{"title":"Hide","path":"/hulipaa-demo/bare-pages/Hide.json","link":"/hulipaa-demo/page/hide.html","numberOfMatches":1},{"title":"Hope","path":"/hulipaa-demo/bare-pages/Hope.json","link":"/hulipaa-demo/page/hope.html","numberOfMatches":1},{"title":"Human","path":"/hulipaa-demo/bare-pages/Human.json","link":"/hulipaa-demo/page/human.html","numberOfMatches":1},{"title":"Independent","path":"/hulipaa-demo/bare-pages/Independent.json","link":"/hulipaa-demo/page/independent.html","numberOfMatches":1},{"title":"Leg","path":"/hulipaa-demo/bare-pages/Leg.json","link":"/hulipaa-demo/page/leg.html","numberOfMatches":1},{"title":"Listen","path":"/hulipaa-demo/bare-pages/Listen.json","link":"/hulipaa-demo/page/listen.html","numberOfMatches":1},{"title":"Local","path":"/hulipaa-demo/bare-pages/Local.json","link":"/hulipaa-demo/page/local.html","numberOfMatches":1},{"title":"Mainly","path":"/hulipaa-demo/bare-pages/Mainly.json","link":"/hulipaa-demo/page/mainly.html","numberOfMatches":1},{"title":"Meal","path":"/hulipaa-demo/bare-pages/Meal.json","link":"/hulipaa-demo/page/meal.html","numberOfMatches":1},{"title":"Mill","path":"/hulipaa-demo/bare-pages/Mill.json","link":"/hulipaa-demo/page/mill.html","numberOfMatches":1},{"title":"Mixture","path":"/hulipaa-demo/bare-pages/Mixture.json","link":"/hulipaa-demo/page/mixture.html","numberOfMatches":1},{"title":"Model","path":"/hulipaa-demo/bare-pages/Model.json","link":"/hulipaa-demo/page/model.html","numberOfMatches":1},{"title":"Must","path":"/hulipaa-demo/bare-pages/Must.json","link":"/hulipaa-demo/page/must.html","numberOfMatches":1},{"title":"Note","path":"/hulipaa-demo/bare-pages/Note.json","link":"/hulipaa-demo/page/note.html","numberOfMatches":1},{"title":"Pan","path":"/hulipaa-demo/bare-pages/Pan.json","link":"/hulipaa-demo/page/pan.html","numberOfMatches":1},{"title":"Piano","path":"/hulipaa-demo/bare-pages/Piano.json","link":"/hulipaa-demo/page/piano.html","numberOfMatches":1},{"title":"Pie","path":"/hulipaa-demo/bare-pages/Pie.json","link":"/hulipaa-demo/page/pie.html","numberOfMatches":1},{"title":"Plan","path":"/hulipaa-demo/bare-pages/Plan.json","link":"/hulipaa-demo/page/plan.html","numberOfMatches":1},{"title":"Plastic","path":"/hulipaa-demo/bare-pages/Plastic.json","link":"/hulipaa-demo/page/plastic.html","numberOfMatches":1},{"title":"Press","path":"/hulipaa-demo/bare-pages/Press.json","link":"/hulipaa-demo/page/press.html","numberOfMatches":1},{"title":"Pretty","path":"/hulipaa-demo/bare-pages/Pretty.json","link":"/hulipaa-demo/page/pretty.html","numberOfMatches":1},{"title":"Seen","path":"/hulipaa-demo/bare-pages/Seen.json","link":"/hulipaa-demo/page/seen.html","numberOfMatches":1},{"title":"Sister","path":"/hulipaa-demo/bare-pages/Sister.json","link":"/hulipaa-demo/page/sister.html","numberOfMatches":1},{"title":"Slipped","path":"/hulipaa-demo/bare-pages/Slipped.json","link":"/hulipaa-demo/page/slipped.html","numberOfMatches":1},{"title":"Soon","path":"/hulipaa-demo/bare-pages/Soon.json","link":"/hulipaa-demo/page/soon.html","numberOfMatches":1},{"title":"Spirit","path":"/hulipaa-demo/bare-pages/Spirit.json","link":"/hulipaa-demo/page/spirit.html","numberOfMatches":1},{"title":"Steam","path":"/hulipaa-demo/bare-pages/Steam.json","link":"/hulipaa-demo/page/steam.html","numberOfMatches":1},{"title":"Stick","path":"/hulipaa-demo/bare-pages/Stick.json","link":"/hulipaa-demo/page/stick.html","numberOfMatches":1},{"title":"Stronger","path":"/hulipaa-demo/bare-pages/Stronger.json","link":"/hulipaa-demo/page/stronger.html","numberOfMatches":1},{"title":"Subject","path":"/hulipaa-demo/bare-pages/Subject.json","link":"/hulipaa-demo/page/subject.html","numberOfMatches":1},{"title":"Test","path":"/hulipaa-demo/bare-pages/Test.json","link":"/hulipaa-demo/page/test.html","numberOfMatches":1},{"title":"Those","path":"/hulipaa-demo/bare-pages/Those.json","link":"/hulipaa-demo/page/those.html","numberOfMatches":1},{"title":"Tonight","path":"/hulipaa-demo/bare-pages/Tonight.json","link":"/hulipaa-demo/page/tonight.html","numberOfMatches":1},{"title":"Try","path":"/hulipaa-demo/bare-pages/Try.json","link":"/hulipaa-demo/page/try.html","numberOfMatches":1},{"title":"Value","path":"/hulipaa-demo/bare-pages/Value.json","link":"/hulipaa-demo/page/value.html","numberOfMatches":1}]}