{"results":[{"title":"Ability","path":"/bare-pages/Ability.json","link":"/page/ability.html","numberOfMatches":1},{"title":"Another","path":"/bare-pages/Another.json","link":"/page/another.html","numberOfMatches":1},{"title":"Arrange","path":"/bare-pages/Arrange.json","link":"/page/arrange.html","numberOfMatches":1},{"title":"Article","path":"/bare-pages/Article.json","link":"/page/article.html","numberOfMatches":1},{"title":"Ask","path":"/bare-pages/Ask.json","link":"/page/ask.html","numberOfMatches":1},{"title":"Automobile","path":"/bare-pages/Automobile.json","link":"/page/automobile.html","numberOfMatches":1},{"title":"Bend","path":"/bare-pages/Bend.json","link":"/page/bend.html","numberOfMatches":1},{"title":"Bowl","path":"/bare-pages/Bowl.json","link":"/page/bowl.html","numberOfMatches":1},{"title":"Brick","path":"/bare-pages/Brick.json","link":"/page/brick.html","numberOfMatches":1},{"title":"Burst","path":"/bare-pages/Burst.json","link":"/page/burst.html","numberOfMatches":1},{"title":"Cloud","path":"/bare-pages/Cloud.json","link":"/page/cloud.html","numberOfMatches":1},{"title":"Completely","path":"/bare-pages/Completely.json","link":"/page/completely.html","numberOfMatches":1},{"title":"Continued","path":"/bare-pages/Continued.json","link":"/page/continued.html","numberOfMatches":3},{"title":"Division","path":"/bare-pages/Division.json","link":"/page/division.html","numberOfMatches":1},{"title":"Driving","path":"/bare-pages/Driving.json","link":"/page/driving.html","numberOfMatches":1},{"title":"Ear","path":"/bare-pages/Ear.json","link":"/page/ear.html","numberOfMatches":1},{"title":"Establish","path":"/bare-pages/Establish.json","link":"/page/establish.html","numberOfMatches":1},{"title":"Fear","path":"/bare-pages/Fear.json","link":"/page/fear.html","numberOfMatches":1},{"title":"Flower","path":"/bare-pages/Flower.json","link":"/page/flower.html","numberOfMatches":1},{"title":"Halfway","path":"/bare-pages/Halfway.json","link":"/page/halfway.html","numberOfMatches":1},{"title":"Huge","path":"/bare-pages/Huge.json","link":"/page/huge.html","numberOfMatches":1},{"title":"Hungry","path":"/bare-pages/Hungry.json","link":"/page/hungry.html","numberOfMatches":1},{"title":"Hurry","path":"/bare-pages/Hurry.json","link":"/page/hurry.html","numberOfMatches":1},{"title":"Imagine","path":"/bare-pages/Imagine.json","link":"/page/imagine.html","numberOfMatches":1},{"title":"Jar","path":"/bare-pages/Jar.json","link":"/page/jar.html","numberOfMatches":1},{"title":"Known","path":"/bare-pages/Known.json","link":"/page/known.html","numberOfMatches":1},{"title":"Lonely","path":"/bare-pages/Lonely.json","link":"/page/lonely.html","numberOfMatches":1},{"title":"Managed","path":"/bare-pages/Managed.json","link":"/page/managed.html","numberOfMatches":1},{"title":"Master","path":"/bare-pages/Master.json","link":"/page/master.html","numberOfMatches":1},{"title":"Metal","path":"/bare-pages/Metal.json","link":"/page/metal.html","numberOfMatches":1},{"title":"Mice","path":"/bare-pages/Mice.json","link":"/page/mice.html","numberOfMatches":1},{"title":"Minerals","path":"/bare-pages/Minerals.json","link":"/page/minerals.html","numberOfMatches":1},{"title":"Moon","path":"/bare-pages/Moon.json","link":"/page/moon.html","numberOfMatches":1},{"title":"Nice","path":"/bare-pages/Nice.json","link":"/page/nice.html","numberOfMatches":1},{"title":"Offer","path":"/bare-pages/Offer.json","link":"/page/offer.html","numberOfMatches":1},{"title":"Onto","path":"/bare-pages/Onto.json","link":"/page/onto.html","numberOfMatches":1},{"title":"Out","path":"/bare-pages/Out.json","link":"/page/out.html","numberOfMatches":1},{"title":"Page","path":"/bare-pages/Page.json","link":"/page/page.html","numberOfMatches":1},{"title":"Palace","path":"/bare-pages/Palace.json","link":"/page/palace.html","numberOfMatches":1},{"title":"People","path":"/bare-pages/People.json","link":"/page/people.html","numberOfMatches":1},{"title":"Please","path":"/bare-pages/Please.json","link":"/page/please.html","numberOfMatches":1},{"title":"Principal","path":"/bare-pages/Principal.json","link":"/page/principal.html","numberOfMatches":1},{"title":"Promised","path":"/bare-pages/Promised.json","link":"/page/promised.html","numberOfMatches":1},{"title":"Ranch","path":"/bare-pages/Ranch.json","link":"/page/ranch.html","numberOfMatches":1},{"title":"Rocky","path":"/bare-pages/Rocky.json","link":"/page/rocky.html","numberOfMatches":1},{"title":"Scale","path":"/bare-pages/Scale.json","link":"/page/scale.html","numberOfMatches":1},{"title":"Seldom","path":"/bare-pages/Seldom.json","link":"/page/seldom.html","numberOfMatches":1},{"title":"Sentence","path":"/bare-pages/Sentence.json","link":"/page/sentence.html","numberOfMatches":1},{"title":"Shade","path":"/bare-pages/Shade.json","link":"/page/shade.html","numberOfMatches":1},{"title":"Shape","path":"/bare-pages/Shape.json","link":"/page/shape.html","numberOfMatches":1},{"title":"Sit","path":"/bare-pages/Sit.json","link":"/page/sit.html","numberOfMatches":1},{"title":"Skin","path":"/bare-pages/Skin.json","link":"/page/skin.html","numberOfMatches":1},{"title":"Small","path":"/bare-pages/Small.json","link":"/page/small.html","numberOfMatches":1},{"title":"Something","path":"/bare-pages/Something.json","link":"/page/something.html","numberOfMatches":1},{"title":"Special","path":"/bare-pages/Special.json","link":"/page/special.html","numberOfMatches":1},{"title":"Store","path":"/bare-pages/Store.json","link":"/page/store.html","numberOfMatches":1},{"title":"Strip","path":"/bare-pages/Strip.json","link":"/page/strip.html","numberOfMatches":1},{"title":"Studying","path":"/bare-pages/Studying.json","link":"/page/studying.html","numberOfMatches":1},{"title":"Swim","path":"/bare-pages/Swim.json","link":"/page/swim.html","numberOfMatches":1},{"title":"Throw","path":"/bare-pages/Throw.json","link":"/page/throw.html","numberOfMatches":1},{"title":"Torn","path":"/bare-pages/Torn.json","link":"/page/torn.html","numberOfMatches":1},{"title":"Treated","path":"/bare-pages/Treated.json","link":"/page/treated.html","numberOfMatches":1},{"title":"Tree","path":"/bare-pages/Tree.json","link":"/page/tree.html","numberOfMatches":1},{"title":"Truck","path":"/bare-pages/Truck.json","link":"/page/truck.html","numberOfMatches":1},{"title":"Try","path":"/bare-pages/Try.json","link":"/page/try.html","numberOfMatches":1},{"title":"Understanding","path":"/bare-pages/Understanding.json","link":"/page/understanding.html","numberOfMatches":1},{"title":"Usually","path":"/bare-pages/Usually.json","link":"/page/usually.html","numberOfMatches":1},{"title":"Very","path":"/bare-pages/Very.json","link":"/page/very.html","numberOfMatches":1},{"title":"Water","path":"/bare-pages/Water.json","link":"/page/water.html","numberOfMatches":1},{"title":"Wood","path":"/bare-pages/Wood.json","link":"/page/wood.html","numberOfMatches":1},{"title":"Zebra","path":"/bare-pages/Zebra.json","link":"/page/zebra.html","numberOfMatches":1},{"title":"Zoo","path":"/bare-pages/Zoo.json","link":"/page/zoo.html","numberOfMatches":1}]}