{"results":[{"title":"Ball","path":"/hulipaa-demo/bare-pages/Ball.json","link":"/hulipaa-demo/page/ball.html","numberOfMatches":1},{"title":"Belong","path":"/hulipaa-demo/bare-pages/Belong.json","link":"/hulipaa-demo/page/belong.html","numberOfMatches":1},{"title":"Bigger","path":"/hulipaa-demo/bare-pages/Bigger.json","link":"/hulipaa-demo/page/bigger.html","numberOfMatches":1},{"title":"Bridge","path":"/hulipaa-demo/bare-pages/Bridge.json","link":"/hulipaa-demo/page/bridge.html","numberOfMatches":1},{"title":"Building","path":"/hulipaa-demo/bare-pages/Building.json","link":"/hulipaa-demo/page/building.html","numberOfMatches":1},{"title":"Cabin","path":"/hulipaa-demo/bare-pages/Cabin.json","link":"/hulipaa-demo/page/cabin.html","numberOfMatches":1},{"title":"Canal","path":"/hulipaa-demo/bare-pages/Canal.json","link":"/hulipaa-demo/page/canal.html","numberOfMatches":1},{"title":"Castle","path":"/hulipaa-demo/bare-pages/Castle.json","link":"/hulipaa-demo/page/castle.html","numberOfMatches":1},{"title":"Changing","path":"/hulipaa-demo/bare-pages/Changing.json","link":"/hulipaa-demo/page/changing.html","numberOfMatches":1},{"title":"Cheese","path":"/hulipaa-demo/bare-pages/Cheese.json","link":"/hulipaa-demo/page/cheese.html","numberOfMatches":1},{"title":"Comfortable","path":"/hulipaa-demo/bare-pages/Comfortable.json","link":"/hulipaa-demo/page/comfortable.html","numberOfMatches":1},{"title":"Construction","path":"/hulipaa-demo/bare-pages/Construction.json","link":"/hulipaa-demo/page/construction.html","numberOfMatches":1},{"title":"Cow","path":"/hulipaa-demo/bare-pages/Cow.json","link":"/hulipaa-demo/page/cow.html","numberOfMatches":1},{"title":"Create","path":"/hulipaa-demo/bare-pages/Create.json","link":"/hulipaa-demo/page/create.html","numberOfMatches":1},{"title":"Deer","path":"/hulipaa-demo/bare-pages/Deer.json","link":"/hulipaa-demo/page/deer.html","numberOfMatches":1},{"title":"Develop","path":"/hulipaa-demo/bare-pages/Develop.json","link":"/hulipaa-demo/page/develop.html","numberOfMatches":1},{"title":"Dried","path":"/hulipaa-demo/bare-pages/Dried.json","link":"/hulipaa-demo/page/dried.html","numberOfMatches":1},{"title":"Dull","path":"/hulipaa-demo/bare-pages/Dull.json","link":"/hulipaa-demo/page/dull.html","numberOfMatches":1},{"title":"Every","path":"/hulipaa-demo/bare-pages/Every.json","link":"/hulipaa-demo/page/every.html","numberOfMatches":1},{"title":"Fought","path":"/hulipaa-demo/bare-pages/Fought.json","link":"/hulipaa-demo/page/fought.html","numberOfMatches":1},{"title":"Funny","path":"/hulipaa-demo/bare-pages/Funny.json","link":"/hulipaa-demo/page/funny.html","numberOfMatches":1},{"title":"Gasoline","path":"/hulipaa-demo/bare-pages/Gasoline.json","link":"/hulipaa-demo/page/gasoline.html","numberOfMatches":1},{"title":"General","path":"/hulipaa-demo/bare-pages/General.json","link":"/hulipaa-demo/page/general.html","numberOfMatches":1},{"title":"Glad","path":"/hulipaa-demo/bare-pages/Glad.json","link":"/hulipaa-demo/page/glad.html","numberOfMatches":1},{"title":"Great","path":"/hulipaa-demo/bare-pages/Great.json","link":"/hulipaa-demo/page/great.html","numberOfMatches":1},{"title":"Greatly","path":"/hulipaa-demo/bare-pages/Greatly.json","link":"/hulipaa-demo/page/greatly.html","numberOfMatches":1},{"title":"Grow","path":"/hulipaa-demo/bare-pages/Grow.json","link":"/hulipaa-demo/page/grow.html","numberOfMatches":1},{"title":"Hang","path":"/hulipaa-demo/bare-pages/Hang.json","link":"/hulipaa-demo/page/hang.html","numberOfMatches":1},{"title":"Happened","path":"/hulipaa-demo/bare-pages/Happened.json","link":"/hulipaa-demo/page/happened.html","numberOfMatches":1},{"title":"Impossible","path":"/hulipaa-demo/bare-pages/Impossible.json","link":"/hulipaa-demo/page/impossible.html","numberOfMatches":1},{"title":"Island","path":"/hulipaa-demo/bare-pages/Island.json","link":"/hulipaa-demo/page/island.html","numberOfMatches":1},{"title":"Leader","path":"/hulipaa-demo/bare-pages/Leader.json","link":"/hulipaa-demo/page/leader.html","numberOfMatches":1},{"title":"Lonely","path":"/hulipaa-demo/bare-pages/Lonely.json","link":"/hulipaa-demo/page/lonely.html","numberOfMatches":1},{"title":"Lying","path":"/hulipaa-demo/bare-pages/Lying.json","link":"/hulipaa-demo/page/lying.html","numberOfMatches":1},{"title":"Manner","path":"/hulipaa-demo/bare-pages/Manner.json","link":"/hulipaa-demo/page/manner.html","numberOfMatches":1},{"title":"May","path":"/hulipaa-demo/bare-pages/May.json","link":"/hulipaa-demo/page/may.html","numberOfMatches":1},{"title":"Molecular","path":"/hulipaa-demo/bare-pages/Molecular.json","link":"/hulipaa-demo/page/molecular.html","numberOfMatches":1},{"title":"Nature","path":"/hulipaa-demo/bare-pages/Nature.json","link":"/hulipaa-demo/page/nature.html","numberOfMatches":1},{"title":"Nearer","path":"/hulipaa-demo/bare-pages/Nearer.json","link":"/hulipaa-demo/page/nearer.html","numberOfMatches":1},{"title":"Newspaper","path":"/hulipaa-demo/bare-pages/Newspaper.json","link":"/hulipaa-demo/page/newspaper.html","numberOfMatches":1},{"title":"North","path":"/hulipaa-demo/bare-pages/North.json","link":"/hulipaa-demo/page/north.html","numberOfMatches":1},{"title":"Numeral","path":"/hulipaa-demo/bare-pages/Numeral.json","link":"/hulipaa-demo/page/numeral.html","numberOfMatches":1},{"title":"Pack","path":"/hulipaa-demo/bare-pages/Pack.json","link":"/hulipaa-demo/page/pack.html","numberOfMatches":1},{"title":"Paid","path":"/hulipaa-demo/bare-pages/Paid.json","link":"/hulipaa-demo/page/paid.html","numberOfMatches":1},{"title":"Particular","path":"/hulipaa-demo/bare-pages/Particular.json","link":"/hulipaa-demo/page/particular.html","numberOfMatches":1},{"title":"Pleasant","path":"/hulipaa-demo/bare-pages/Pleasant.json","link":"/hulipaa-demo/page/pleasant.html","numberOfMatches":1},{"title":"Produce","path":"/hulipaa-demo/bare-pages/Produce.json","link":"/hulipaa-demo/page/produce.html","numberOfMatches":1},{"title":"Putting","path":"/hulipaa-demo/bare-pages/Putting.json","link":"/hulipaa-demo/page/putting.html","numberOfMatches":1},{"title":"Rapidly","path":"/hulipaa-demo/bare-pages/Rapidly.json","link":"/hulipaa-demo/page/rapidly.html","numberOfMatches":1},{"title":"Right","path":"/hulipaa-demo/bare-pages/Right.json","link":"/hulipaa-demo/page/right.html","numberOfMatches":1},{"title":"Rod","path":"/hulipaa-demo/bare-pages/Rod.json","link":"/hulipaa-demo/page/rod.html","numberOfMatches":1},{"title":"Sand","path":"/hulipaa-demo/bare-pages/Sand.json","link":"/hulipaa-demo/page/sand.html","numberOfMatches":1},{"title":"Scale","path":"/hulipaa-demo/bare-pages/Scale.json","link":"/hulipaa-demo/page/scale.html","numberOfMatches":1},{"title":"See","path":"/hulipaa-demo/bare-pages/See.json","link":"/hulipaa-demo/page/see.html","numberOfMatches":1},{"title":"Shore","path":"/hulipaa-demo/bare-pages/Shore.json","link":"/hulipaa-demo/page/shore.html","numberOfMatches":1},{"title":"Sides","path":"/hulipaa-demo/bare-pages/Sides.json","link":"/hulipaa-demo/page/sides.html","numberOfMatches":1},{"title":"Speech","path":"/hulipaa-demo/bare-pages/Speech.json","link":"/hulipaa-demo/page/speech.html","numberOfMatches":2},{"title":"Spirit","path":"/hulipaa-demo/bare-pages/Spirit.json","link":"/hulipaa-demo/page/spirit.html","numberOfMatches":1},{"title":"Stomach","path":"/hulipaa-demo/bare-pages/Stomach.json","link":"/hulipaa-demo/page/stomach.html","numberOfMatches":1},{"title":"Strange","path":"/hulipaa-demo/bare-pages/Strange.json","link":"/hulipaa-demo/page/strange.html","numberOfMatches":1},{"title":"Stranger","path":"/hulipaa-demo/bare-pages/Stranger.json","link":"/hulipaa-demo/page/stranger.html","numberOfMatches":1},{"title":"Structure","path":"/hulipaa-demo/bare-pages/Structure.json","link":"/hulipaa-demo/page/structure.html","numberOfMatches":1},{"title":"Swim","path":"/hulipaa-demo/bare-pages/Swim.json","link":"/hulipaa-demo/page/swim.html","numberOfMatches":1},{"title":"Thank","path":"/hulipaa-demo/bare-pages/Thank.json","link":"/hulipaa-demo/page/thank.html","numberOfMatches":1},{"title":"There","path":"/hulipaa-demo/bare-pages/There.json","link":"/hulipaa-demo/page/there.html","numberOfMatches":1},{"title":"Thou","path":"/hulipaa-demo/bare-pages/Thou.json","link":"/hulipaa-demo/page/thou.html","numberOfMatches":2},{"title":"Three","path":"/hulipaa-demo/bare-pages/Three.json","link":"/hulipaa-demo/page/three.html","numberOfMatches":1},{"title":"Tobacco","path":"/hulipaa-demo/bare-pages/Tobacco.json","link":"/hulipaa-demo/page/tobacco.html","numberOfMatches":1},{"title":"Tongue","path":"/hulipaa-demo/bare-pages/Tongue.json","link":"/hulipaa-demo/page/tongue.html","numberOfMatches":1},{"title":"Topic","path":"/hulipaa-demo/bare-pages/Topic.json","link":"/hulipaa-demo/page/topic.html","numberOfMatches":1},{"title":"Tower","path":"/hulipaa-demo/bare-pages/Tower.json","link":"/hulipaa-demo/page/tower.html","numberOfMatches":1},{"title":"Tube","path":"/hulipaa-demo/bare-pages/Tube.json","link":"/hulipaa-demo/page/tube.html","numberOfMatches":1},{"title":"Usual","path":"/hulipaa-demo/bare-pages/Usual.json","link":"/hulipaa-demo/page/usual.html","numberOfMatches":1},{"title":"Vapor","path":"/hulipaa-demo/bare-pages/Vapor.json","link":"/hulipaa-demo/page/vapor.html","numberOfMatches":1},{"title":"Wear","path":"/hulipaa-demo/bare-pages/Wear.json","link":"/hulipaa-demo/page/wear.html","numberOfMatches":1},{"title":"Weight","path":"/hulipaa-demo/bare-pages/Weight.json","link":"/hulipaa-demo/page/weight.html","numberOfMatches":1},{"title":"Win","path":"/hulipaa-demo/bare-pages/Win.json","link":"/hulipaa-demo/page/win.html","numberOfMatches":1},{"title":"Window","path":"/hulipaa-demo/bare-pages/Window.json","link":"/hulipaa-demo/page/window.html","numberOfMatches":1}]}