{"results":[{"title":"Afraid","path":"/hulipaa-demo/bare-pages/Afraid.json","link":"/hulipaa-demo/page/afraid.html","numberOfMatches":1},{"title":"Aloud","path":"/hulipaa-demo/bare-pages/Aloud.json","link":"/hulipaa-demo/page/aloud.html","numberOfMatches":1},{"title":"Ancient","path":"/hulipaa-demo/bare-pages/Ancient.json","link":"/hulipaa-demo/page/ancient.html","numberOfMatches":1},{"title":"Announced","path":"/hulipaa-demo/bare-pages/Announced.json","link":"/hulipaa-demo/page/announced.html","numberOfMatches":1},{"title":"Away","path":"/hulipaa-demo/bare-pages/Away.json","link":"/hulipaa-demo/page/away.html","numberOfMatches":1},{"title":"Before","path":"/hulipaa-demo/bare-pages/Before.json","link":"/hulipaa-demo/page/before.html","numberOfMatches":1},{"title":"Being","path":"/hulipaa-demo/bare-pages/Being.json","link":"/hulipaa-demo/page/being.html","numberOfMatches":1},{"title":"Blind","path":"/hulipaa-demo/bare-pages/Blind.json","link":"/hulipaa-demo/page/blind.html","numberOfMatches":1},{"title":"Brush","path":"/hulipaa-demo/bare-pages/Brush.json","link":"/hulipaa-demo/page/brush.html","numberOfMatches":1},{"title":"Century","path":"/hulipaa-demo/bare-pages/Century.json","link":"/hulipaa-demo/page/century.html","numberOfMatches":1},{"title":"Certainly","path":"/hulipaa-demo/bare-pages/Certainly.json","link":"/hulipaa-demo/page/certainly.html","numberOfMatches":1},{"title":"Character","path":"/hulipaa-demo/bare-pages/Character.json","link":"/hulipaa-demo/page/character.html","numberOfMatches":1},{"title":"Close","path":"/hulipaa-demo/bare-pages/Close.json","link":"/hulipaa-demo/page/close.html","numberOfMatches":1},{"title":"Cold","path":"/hulipaa-demo/bare-pages/Cold.json","link":"/hulipaa-demo/page/cold.html","numberOfMatches":1},{"title":"College","path":"/hulipaa-demo/bare-pages/College.json","link":"/hulipaa-demo/page/college.html","numberOfMatches":1},{"title":"Combination","path":"/hulipaa-demo/bare-pages/Combination.json","link":"/hulipaa-demo/page/combination.html","numberOfMatches":1},{"title":"Corner","path":"/hulipaa-demo/bare-pages/Corner.json","link":"/hulipaa-demo/page/corner.html","numberOfMatches":1},{"title":"Cover","path":"/hulipaa-demo/bare-pages/Cover.json","link":"/hulipaa-demo/page/cover.html","numberOfMatches":1},{"title":"Crew","path":"/hulipaa-demo/bare-pages/Crew.json","link":"/hulipaa-demo/page/crew.html","numberOfMatches":1},{"title":"Damage","path":"/hulipaa-demo/bare-pages/Damage.json","link":"/hulipaa-demo/page/damage.html","numberOfMatches":1},{"title":"Feathers","path":"/hulipaa-demo/bare-pages/Feathers.json","link":"/hulipaa-demo/page/feathers.html","numberOfMatches":1},{"title":"Feed","path":"/hulipaa-demo/bare-pages/Feed.json","link":"/hulipaa-demo/page/feed.html","numberOfMatches":1},{"title":"Follow","path":"/hulipaa-demo/bare-pages/Follow.json","link":"/hulipaa-demo/page/follow.html","numberOfMatches":1},{"title":"For","path":"/hulipaa-demo/bare-pages/For.json","link":"/hulipaa-demo/page/for.html","numberOfMatches":1},{"title":"Forgot","path":"/hulipaa-demo/bare-pages/Forgot.json","link":"/hulipaa-demo/page/forgot.html","numberOfMatches":1},{"title":"Giving","path":"/hulipaa-demo/bare-pages/Giving.json","link":"/hulipaa-demo/page/giving.html","numberOfMatches":1},{"title":"Gold","path":"/hulipaa-demo/bare-pages/Gold.json","link":"/hulipaa-demo/page/gold.html","numberOfMatches":1},{"title":"Green","path":"/hulipaa-demo/bare-pages/Green.json","link":"/hulipaa-demo/page/green.html","numberOfMatches":1},{"title":"Hearing","path":"/hulipaa-demo/bare-pages/Hearing.json","link":"/hulipaa-demo/page/hearing.html","numberOfMatches":1},{"title":"Hollow","path":"/hulipaa-demo/bare-pages/Hollow.json","link":"/hulipaa-demo/page/hollow.html","numberOfMatches":1},{"title":"Hope","path":"/hulipaa-demo/bare-pages/Hope.json","link":"/hulipaa-demo/page/hope.html","numberOfMatches":1},{"title":"In","path":"/hulipaa-demo/bare-pages/In.json","link":"/hulipaa-demo/page/in.html","numberOfMatches":1},{"title":"Jack","path":"/hulipaa-demo/bare-pages/Jack.json","link":"/hulipaa-demo/page/jack.html","numberOfMatches":1},{"title":"Life","path":"/hulipaa-demo/bare-pages/Life.json","link":"/hulipaa-demo/page/life.html","numberOfMatches":1},{"title":"Lift","path":"/hulipaa-demo/bare-pages/Lift.json","link":"/hulipaa-demo/page/lift.html","numberOfMatches":1},{"title":"Loose","path":"/hulipaa-demo/bare-pages/Loose.json","link":"/hulipaa-demo/page/loose.html","numberOfMatches":1},{"title":"Method","path":"/hulipaa-demo/bare-pages/Method.json","link":"/hulipaa-demo/page/method.html","numberOfMatches":1},{"title":"Month","path":"/hulipaa-demo/bare-pages/Month.json","link":"/hulipaa-demo/page/month.html","numberOfMatches":1},{"title":"Movement","path":"/hulipaa-demo/bare-pages/Movement.json","link":"/hulipaa-demo/page/movement.html","numberOfMatches":1},{"title":"Musical","path":"/hulipaa-demo/bare-pages/Musical.json","link":"/hulipaa-demo/page/musical.html","numberOfMatches":1},{"title":"Never","path":"/hulipaa-demo/bare-pages/Never.json","link":"/hulipaa-demo/page/never.html","numberOfMatches":1},{"title":"Nothing","path":"/hulipaa-demo/bare-pages/Nothing.json","link":"/hulipaa-demo/page/nothing.html","numberOfMatches":1},{"title":"On","path":"/hulipaa-demo/bare-pages/On.json","link":"/hulipaa-demo/page/on.html","numberOfMatches":1},{"title":"Region","path":"/hulipaa-demo/bare-pages/Region.json","link":"/hulipaa-demo/page/region.html","numberOfMatches":1},{"title":"Room","path":"/hulipaa-demo/bare-pages/Room.json","link":"/hulipaa-demo/page/room.html","numberOfMatches":1},{"title":"Round","path":"/hulipaa-demo/bare-pages/Round.json","link":"/hulipaa-demo/page/round.html","numberOfMatches":1},{"title":"Ruler","path":"/hulipaa-demo/bare-pages/Ruler.json","link":"/hulipaa-demo/page/ruler.html","numberOfMatches":1},{"title":"Satellites","path":"/hulipaa-demo/bare-pages/Satellites.json","link":"/hulipaa-demo/page/satellites.html","numberOfMatches":1},{"title":"Scared","path":"/hulipaa-demo/bare-pages/Scared.json","link":"/hulipaa-demo/page/scared.html","numberOfMatches":1},{"title":"Sense","path":"/hulipaa-demo/bare-pages/Sense.json","link":"/hulipaa-demo/page/sense.html","numberOfMatches":1},{"title":"Sent","path":"/hulipaa-demo/bare-pages/Sent.json","link":"/hulipaa-demo/page/sent.html","numberOfMatches":1},{"title":"Sight","path":"/hulipaa-demo/bare-pages/Sight.json","link":"/hulipaa-demo/page/sight.html","numberOfMatches":1},{"title":"Silk","path":"/hulipaa-demo/bare-pages/Silk.json","link":"/hulipaa-demo/page/silk.html","numberOfMatches":1},{"title":"Sport","path":"/hulipaa-demo/bare-pages/Sport.json","link":"/hulipaa-demo/page/sport.html","numberOfMatches":1},{"title":"Sunlight","path":"/hulipaa-demo/bare-pages/Sunlight.json","link":"/hulipaa-demo/page/sunlight.html","numberOfMatches":1},{"title":"Support","path":"/hulipaa-demo/bare-pages/Support.json","link":"/hulipaa-demo/page/support.html","numberOfMatches":1},{"title":"Thought","path":"/hulipaa-demo/bare-pages/Thought.json","link":"/hulipaa-demo/page/thought.html","numberOfMatches":1},{"title":"Tip","path":"/hulipaa-demo/bare-pages/Tip.json","link":"/hulipaa-demo/page/tip.html","numberOfMatches":1},{"title":"Took","path":"/hulipaa-demo/bare-pages/Took.json","link":"/hulipaa-demo/page/took.html","numberOfMatches":1},{"title":"Trace","path":"/hulipaa-demo/bare-pages/Trace.json","link":"/hulipaa-demo/page/trace.html","numberOfMatches":1},{"title":"Verb","path":"/hulipaa-demo/bare-pages/Verb.json","link":"/hulipaa-demo/page/verb.html","numberOfMatches":1},{"title":"Work","path":"/hulipaa-demo/bare-pages/Work.json","link":"/hulipaa-demo/page/work.html","numberOfMatches":1},{"title":"Yard","path":"/hulipaa-demo/bare-pages/Yard.json","link":"/hulipaa-demo/page/yard.html","numberOfMatches":2},{"title":"Young","path":"/hulipaa-demo/bare-pages/Young.json","link":"/hulipaa-demo/page/young.html","numberOfMatches":1}]}