{"results":[{"title":"Actual","path":"/bare-pages/Actual.json","link":"/page/actual.html","numberOfMatches":1},{"title":"Allow","path":"/bare-pages/Allow.json","link":"/page/allow.html","numberOfMatches":1},{"title":"Ancient","path":"/bare-pages/Ancient.json","link":"/page/ancient.html","numberOfMatches":1},{"title":"Arrow","path":"/bare-pages/Arrow.json","link":"/page/arrow.html","numberOfMatches":1},{"title":"Blow","path":"/bare-pages/Blow.json","link":"/page/blow.html","numberOfMatches":1},{"title":"Both","path":"/bare-pages/Both.json","link":"/page/both.html","numberOfMatches":1},{"title":"Broad","path":"/bare-pages/Broad.json","link":"/page/broad.html","numberOfMatches":1},{"title":"Chance","path":"/bare-pages/Chance.json","link":"/page/chance.html","numberOfMatches":1},{"title":"Completely","path":"/bare-pages/Completely.json","link":"/page/completely.html","numberOfMatches":1},{"title":"Course","path":"/bare-pages/Course.json","link":"/page/course.html","numberOfMatches":1},{"title":"Creature","path":"/bare-pages/Creature.json","link":"/page/creature.html","numberOfMatches":1},{"title":"Daughter","path":"/bare-pages/Daughter.json","link":"/page/daughter.html","numberOfMatches":1},{"title":"Earth","path":"/bare-pages/Earth.json","link":"/page/earth.html","numberOfMatches":1},{"title":"Engine","path":"/bare-pages/Engine.json","link":"/page/engine.html","numberOfMatches":1},{"title":"Forgot","path":"/bare-pages/Forgot.json","link":"/page/forgot.html","numberOfMatches":1},{"title":"Glad","path":"/bare-pages/Glad.json","link":"/page/glad.html","numberOfMatches":1},{"title":"Great","path":"/bare-pages/Great.json","link":"/page/great.html","numberOfMatches":1},{"title":"Greater","path":"/bare-pages/Greater.json","link":"/page/greater.html","numberOfMatches":1},{"title":"Happy","path":"/bare-pages/Happy.json","link":"/page/happy.html","numberOfMatches":1},{"title":"Hidden","path":"/bare-pages/Hidden.json","link":"/page/hidden.html","numberOfMatches":1},{"title":"However","path":"/bare-pages/However.json","link":"/page/however.html","numberOfMatches":1},{"title":"Husband","path":"/bare-pages/Husband.json","link":"/page/husband.html","numberOfMatches":1},{"title":"Instrument","path":"/bare-pages/Instrument.json","link":"/page/instrument.html","numberOfMatches":1},{"title":"Kids","path":"/bare-pages/Kids.json","link":"/page/kids.html","numberOfMatches":1},{"title":"Lost","path":"/bare-pages/Lost.json","link":"/page/lost.html","numberOfMatches":1},{"title":"Means","path":"/bare-pages/Means.json","link":"/page/means.html","numberOfMatches":1},{"title":"Mice","path":"/bare-pages/Mice.json","link":"/page/mice.html","numberOfMatches":1},{"title":"Missing","path":"/bare-pages/Missing.json","link":"/page/missing.html","numberOfMatches":1},{"title":"Moon","path":"/bare-pages/Moon.json","link":"/page/moon.html","numberOfMatches":1},{"title":"Mouth","path":"/bare-pages/Mouth.json","link":"/page/mouth.html","numberOfMatches":1},{"title":"Natural","path":"/bare-pages/Natural.json","link":"/page/natural.html","numberOfMatches":1},{"title":"Nearly","path":"/bare-pages/Nearly.json","link":"/page/nearly.html","numberOfMatches":1},{"title":"Noun","path":"/bare-pages/Noun.json","link":"/page/noun.html","numberOfMatches":1},{"title":"Now","path":"/bare-pages/Now.json","link":"/page/now.html","numberOfMatches":1},{"title":"Order","path":"/bare-pages/Order.json","link":"/page/order.html","numberOfMatches":1},{"title":"Printed","path":"/bare-pages/Printed.json","link":"/page/printed.html","numberOfMatches":1},{"title":"Probably","path":"/bare-pages/Probably.json","link":"/page/probably.html","numberOfMatches":1},{"title":"Program","path":"/bare-pages/Program.json","link":"/page/program.html","numberOfMatches":1},{"title":"Putting","path":"/bare-pages/Putting.json","link":"/page/putting.html","numberOfMatches":1},{"title":"Ranch","path":"/bare-pages/Ranch.json","link":"/page/ranch.html","numberOfMatches":1},{"title":"Rate","path":"/bare-pages/Rate.json","link":"/page/rate.html","numberOfMatches":1},{"title":"Relationship","path":"/bare-pages/Relationship.json","link":"/page/relationship.html","numberOfMatches":1},{"title":"Sand","path":"/bare-pages/Sand.json","link":"/page/sand.html","numberOfMatches":1},{"title":"Shape","path":"/bare-pages/Shape.json","link":"/page/shape.html","numberOfMatches":1},{"title":"Shelf","path":"/bare-pages/Shelf.json","link":"/page/shelf.html","numberOfMatches":1},{"title":"Skin","path":"/bare-pages/Skin.json","link":"/page/skin.html","numberOfMatches":1},{"title":"Smaller","path":"/bare-pages/Smaller.json","link":"/page/smaller.html","numberOfMatches":1},{"title":"Table","path":"/bare-pages/Table.json","link":"/page/table.html","numberOfMatches":1},{"title":"Television","path":"/bare-pages/Television.json","link":"/page/television.html","numberOfMatches":1},{"title":"Third","path":"/bare-pages/Third.json","link":"/page/third.html","numberOfMatches":1},{"title":"Use","path":"/bare-pages/Use.json","link":"/page/use.html","numberOfMatches":1},{"title":"Watch","path":"/bare-pages/Watch.json","link":"/page/watch.html","numberOfMatches":1},{"title":"Way","path":"/bare-pages/Way.json","link":"/page/way.html","numberOfMatches":1},{"title":"Window","path":"/bare-pages/Window.json","link":"/page/window.html","numberOfMatches":1},{"title":"Zipper","path":"/bare-pages/Zipper.json","link":"/page/zipper.html","numberOfMatches":1}]}